PypeDreams/__init__.py
PypeDreams/adjectives.py
PypeDreams/animals.py
PypeDreams/clothing.py
PypeDreams/colors.py
PypeDreams/compress.py
PypeDreams/pype_dreams.py
PypeDreams-0.0.1.dist-info/LICENSE
PypeDreams-0.0.1.dist-info/METADATA
PypeDreams-0.0.1.dist-info/WHEEL
PypeDreams-0.0.1.dist-info/entry_points.txt
PypeDreams-0.0.1.dist-info/top_level.txt
PypeDreams-0.0.1.dist-info/RECORD
