Metadata-Version: 2.1
Name: PypeDreams
Version: 0.0.1
Summary: PypeDreams generates easy to remember animal-based hash digests
Author-email: Huth S0lo <john@themorphium.io>
License: Apache License
Project-URL: Homepage, https://github.com/themorphium/pype_dreams
Keywords: python,cardano,naming,hash
Classifier: License :: OSI Approved :: Apache Software License
Classifier: Programming Language :: Python
Classifier: Programming Language :: Python :: 3
Requires-Python: >=3.9
License-File: LICENSE
Provides-Extra: dev
Requires-Dist: black ; extra == 'dev'
Requires-Dist: bumpver ; extra == 'dev'
Requires-Dist: isort ; extra == 'dev'
Requires-Dist: pip-tools ; extra == 'dev'
Requires-Dist: pytest ; extra == 'dev'
